<?xml version = '1.0' encoding = 'UTF-8'?>
<FKIndexAssociation class="oracle.dbtools.crest.model.design.relational.FKIndexAssociation" directorySegmentName="seg_0" id="E432A1E9-F4D4-4ABB-ABC6-91DE6DA464A8" containerWithKeyObject="573A9452-E0AA-FFFD-93DB-BA42E567FDB2" localFKIndex="3EB7F08A-A03F-047D-3CC3-DE3E9647F088" name="TBL_E_P_B_TBL_E_FK">
<createdBy>steph</createdBy>
<createdTime>2024-04-21 04:36:38 UTC</createdTime>
<ownerDesignName>Modelo_BD_Aerolinea</ownerDesignName>
<referredTableLongName>TBL_EQUIPAJES</referredTableLongName>
<deleteRule>NO ACTION</deleteRule>
<referredTableID>6620661E-2EF5-78FF-ED40-218F6AA546D6</referredTableID>
<keyObject>48CE95C4-7057-76FC-1EBC-7E125F507BC7</keyObject>
<referredKeyID>48CE95C4-7057-76FC-1EBC-7E125F507BC7</referredKeyID>
<mandatory>true</mandatory>
<refColNames>ID_EQUIPAJE</refColNames>
<transferable>true</transferable>
<rely>false</rely>
<columnDependencyConstraintGenerateInDDL>true</columnDependencyConstraintGenerateInDDL>
</FKIndexAssociation>